Metadata-Version: 1.1
Name: tap-fixerio
Version: 0.1.3
Summary: Singer.io tap for extracting currency exchange rate data from the fixer.io API
Home-page: http://singer.io
Author: Stitch
Author-email: UNKNOWN
License: UNKNOWN
Platform: UNKNOWN
Classifier: Programming Language :: Python :: 3 :: Only
